textdb/__init__.py
textdb/manager.py
textdb-0.0.2.dist-info/LICENCE
textdb-0.0.2.dist-info/METADATA
textdb-0.0.2.dist-info/WHEEL
textdb-0.0.2.dist-info/top_level.txt
textdb-0.0.2.dist-info/RECORD
